setup.py
twittytwister/__init__.py
twittytwister/_version.py
twittytwister/twitter.py
twittytwister/txml.py
twittytwister.egg-info/PKG-INFO
twittytwister.egg-info/SOURCES.txt
twittytwister.egg-info/dependency_links.txt
twittytwister.egg-info/top_level.txt