Metadata-Version: 1.1
Name: twittytwister
Version: 0.1.0
Summary: Twitter client for Twisted Python
Home-page: http://github.com/dustin/twitty-twister/
Author: Oliver Gould
Author-email: ver@olix0r.net
License: MIT
Download-URL: http://pypi.python.org/pypi/twittytwister
Platform: any
Classifier: Framework :: Twisted
Classifier: Intended Audience :: Developers
Classifier: License :: OSI Approved :: MIT License
Requires: oauth
Requires: twisted
Requires: twisted.web
